OmicsTools/__init__.py
OmicsTools/counts.py
OmicsTools/namespace.py
OmicsTools/enrich/__init__.py
OmicsTools/enrich/go.py
OmicsTools/enrich/db/go-basic.pkl
OmicsTools/enrich/db/symbol2go.pkl
OmicsTools-0.3.8.dist-info/METADATA
OmicsTools-0.3.8.dist-info/RECORD
OmicsTools-0.3.8.dist-info/WHEEL
OmicsTools-0.3.8.dist-info/top_level.txt
