Metadata-Version: 2.1
Name: OmicsTools
Version: 0.3.8
Summary: UNKNOWN
Home-page: https://github.com/fraenkel-lab/OmicsTools
Author: iamjli
Author-email: iamjli@mit.edu
License: MIT
Platform: UNKNOWN
Classifier: Programming Language :: Python :: 3.5
Classifier: Programming Language :: Python :: 3.6
Classifier: Programming Language :: Python :: 3.7
Requires-Python: >=3.5
Requires-Dist: pandas (>=0.20.1)
Requires-Dist: numpy (>=1.12.0)
Requires-Dist: networkx (>=2.0)
Requires-Dist: mygene (==3.1.0)
Requires-Dist: goenrich (==1.11)
